transipApiV6/Domains.py
transipApiV6/Generic.py
transipApiV6/__init__.py
transipApiV6/setup.py
transipApiV6-0.0.2.dist-info/LICENSE
transipApiV6-0.0.2.dist-info/METADATA
transipApiV6-0.0.2.dist-info/WHEEL
transipApiV6-0.0.2.dist-info/top_level.txt
transipApiV6-0.0.2.dist-info/RECORD
