Metadata-Version: 2.1
Name: transipApiV6
Version: 0.0.2
Summary: Package to interact with the V6 API of Transip 
Home-page: https://github.com/jeromba6/transip_api_v6
Author: Jeroen van Gemert
Author-email: pypi@jeroen.van.gemert.net
License: UNKNOWN
Platform: UNKNOWN
Classifier: Programming Language :: Python :: 3
Classifier: License :: OSI Approved :: MIT License
Classifier: Operating System :: OS Independent
Requires-Python: >=3.x
